MANIFEST.in
README.md
setup.py
nornir_junos/__init__.py
nornir_junos.egg-info/PKG-INFO
nornir_junos.egg-info/SOURCES.txt
nornir_junos.egg-info/dependency_links.txt
nornir_junos.egg-info/requires.txt
nornir_junos.egg-info/top_level.txt
nornir_junos/connections/__init__.py
nornir_junos/tasks/__init__.py
nornir_junos/tasks/junos_config.py
nornir_junos/tasks/junos_get.py
nornir_junos/tasks/junos_rpc.py
nornir_junos/tasks/report.py
nornir_junos/tasks/junos_views/__init__.py
nornir_junos/tasks/junos_views/__init__.yml
nornir_junos/tasks/junos_views/alarms.yml
nornir_junos/tasks/junos_views/bgp.yml
nornir_junos/tasks/junos_views/chassis.yml
nornir_junos/tasks/junos_views/interface.yml
nornir_junos/tasks/junos_views/isis.yml
nornir_junos/tasks/junos_views/lldp.yml
nornir_junos/tasks/junos_views/rsvp.yml
nornir_junos/tasks/junos_views/system_commit.yml
nornir_junos/tasks/junos_views/system_version.yml